Sixpack-2.7.0.data/scripts/sixpack
Sixpack-2.7.0.data/scripts/sixpack-web
Sixpack-2.7.0.dist-info/DESCRIPTION.rst
Sixpack-2.7.0.dist-info/METADATA
Sixpack-2.7.0.dist-info/RECORD
Sixpack-2.7.0.dist-info/WHEEL
Sixpack-2.7.0.dist-info/metadata.json
Sixpack-2.7.0.dist-info/top_level.txt
sixpack/__init__.py
sixpack/analysis.py
sixpack/api.py
sixpack/config.py
sixpack/db.py
sixpack/metrics.py
sixpack/models.py
sixpack/server.py
sixpack/utils.py
sixpack/web.py
sixpack/static/.webassets-cache/.gitkeep
sixpack/static/.webassets-cache/065b774b6a89aac60698104db007c73a
sixpack/static/.webassets-cache/1912ba88a9a89d824ad4ce90d051f04a
sixpack/static/.webassets-cache/25fb23affed15b642fa02b246cc14d89
sixpack/static/.webassets-cache/2ba97ee2511403296a1439491c8ee0bf
sixpack/static/.webassets-cache/56d42299c2a405fa86f1b9dfb953a076
sixpack/static/.webassets-cache/82f6f813be26bc574e11824900910830
sixpack/static/.webassets-cache/8ef21409c051a49fc66c26ecddb05e4f
sixpack/static/.webassets-cache/b969e4285d6fd74df95ad1d67d1428d6
sixpack/static/.webassets-cache/bda63bb7b4c7f3b9a84f684e2a4047a7
sixpack/static/.webassets-cache/cf7fa6b9558fba0c99289fd566568671
sixpack/static/css/sixpack.css
sixpack/static/css/vendor/bootstrap-responsive.css
sixpack/static/css/vendor/bootstrap-responsive.min.css
sixpack/static/css/vendor/bootstrap.css
sixpack/static/css/vendor/bootstrap.min.css
sixpack/static/flash/ZeroClipboard.swf
sixpack/static/gen/.gitkeep
sixpack/static/gen/sixpack.css
sixpack/static/gen/sixpack.js
sixpack/static/img/background-gradient.png
sixpack/static/img/background-tile.png
sixpack/static/img/favicon.png
sixpack/static/img/glyphicons-halflings-white.png
sixpack/static/img/glyphicons-halflings.png
sixpack/static/img/logo.png
sixpack/static/img/logo@2x.png
sixpack/static/js/chart.js
sixpack/static/js/experiment.js
sixpack/static/js/sixpack.js
sixpack/static/js/vendor/bootstrap.js
sixpack/static/js/vendor/bootstrap.min.js
sixpack/static/js/vendor/d3.js
sixpack/static/js/vendor/jquery.js
sixpack/static/js/vendor/spin.min.js
sixpack/static/js/vendor/underscore-min.js
sixpack/static/js/vendor/waypoints.min.js
