Metadata-Version: 2.0
Name: Sixpack
Version: 2.7.0
Summary: A/B testing framework under active development at SeatGeek
Home-page: http://github.com/seatgeek/sixpack
Author: SeatGeek
Author-email: hi@seatgeek.com
License: Copyright (c) 2015, SeatGeek, Inc.
Requires-Dist: Flask (==0.10)
Requires-Dist: Flask-Assets (==0.12)
Requires-Dist: Flask-Cors (==2.0.1)
Requires-Dist: Flask-DebugToolbar (==0.7.1)
Requires-Dist: Flask-SeaSurf (==0.1.13)
Requires-Dist: Markdown (==2.3.1)
Requires-Dist: PyYAML (==3.10)
Requires-Dist: Werkzeug (==0.9.1)
Requires-Dist: closure (==20121212)
Requires-Dist: decorator (==3.3.2)
Requires-Dist: fakeredis (==0.4.0)
Requires-Dist: gevent (==1.1.2)
Requires-Dist: gunicorn (>=17.5,<=19.4.1)
Requires-Dist: hiredis (==0.1.4)
Requires-Dist: jsmin (==2.0.2-1)
Requires-Dist: mock (==1.0.1)
Requires-Dist: python-coveralls (==2.4.3)
Requires-Dist: python-dateutil (==1.5)
Requires-Dist: redis (==2.9.0)
Requires-Dist: statsd (==3.2.1)
Requires-Dist: yuicompressor (==2.4.7)
